mahlkoenig/__init__.py
mahlkoenig/exceptions.py
mahlkoenig/models.py
mahlkoenig-0.5.1.dist-info/licenses/LICENSE
mahlkoenig-0.5.1.dist-info/METADATA
mahlkoenig-0.5.1.dist-info/WHEEL
mahlkoenig-0.5.1.dist-info/top_level.txt
mahlkoenig-0.5.1.dist-info/RECORD
