Metadata-Version: 2.4
Name: mahlkoenig
Version: 0.5.1
Summary: Async client library for the Mahlkönig X54 grinder
Author-email: Kevin Schweikert <kevin@kevinschweikert.de>
License-Expression: MIT
Project-URL: Changelog, https://github.com/kevinschweikert/mahlkoenig/blob/main/CHANGELOG.md
Project-URL: Issues, https://github.com/kevinschweikert/mahlkoenig/issues
Project-URL: Repository, https://github.com/kevinschweikert/mahlkoenig.git
Classifier: Programming Language :: Python :: 3 :: Only
Classifier: Programming Language :: Python :: 3.11
Classifier: Programming Language :: Python :: 3.12
Classifier: Programming Language :: Python :: 3.13
Requires-Python: >=3.11
License-File: LICENSE
Requires-Dist: aiohttp>=3.11
Requires-Dist: pydantic>=2.10
Requires-Dist: pydantic-extra-types>=2.10.4
Dynamic: license-file
